glabpkg/__init__.py
glabpkg/version.py
glabpkg/base/__init__.py
glabpkg/base/option.py
glabpkg/base/resource/.gitattributes.tpl
glabpkg/base/resource/.gitlab-ci.yml
glabpkg/base/resource/.gitlab/issue_templates/bug.md
glabpkg/base/resource/.gitlab/issue_templates/feature.md
glabpkg/base/resource/.gitlab/issue_templates/technical_task.md
glabpkg/data/__init__.py
glabpkg/data/option.py
glabpkg/data/resource/raw/readme.rst
glabpkg/data/resource/script/readme.rst
glabpkg/data/resource/src/{{ base.pkgname }}/__init__.py.tpl
glabpkg/data/resource/src/{{ base.pkgname }}/info.py.tpl
glabpkg/data/resource/src/{{ base.pkgname }}/clean/readme.rst
glabpkg/data/resource/test/test_packaging.py.tpl
glabpkg/pkg/__init__.py
glabpkg/pkg/option.py
glabpkg/pkg/resource/doc/installation.rst
glabpkg/pkg/resource/doc/badges/badge_pkging_conda.svg
glabpkg/pkg/resource/doc/badges/badge_pkging_pip.svg
glabpkg/pkg/resource/doc/badges/listing.rst
glabpkg/pkg_dev/__init__.py
glabpkg/pkg_dev/option.py
glabpkg/pkg_dev/resource/.gitlab-ci.yml
glabpkg/pkg_dev/resource/README.rst
glabpkg/pkg_dev/resource/doc/authors.rst
glabpkg/pkg_dev/resource/doc/contributing.rst
glabpkg/pkg_dev/resource/doc/history.rst
glabpkg/pkg_dev/resource/doc/index.rst
glabpkg/pkg_dev/resource/doc/installation.rst
glabpkg/pkg_dev/resource/doc/management.rst
glabpkg/pkg_dev/resource/doc/readme.rst
glabpkg/pkg_dev/resource/doc/usage.rst
glabpkg/pkg_dev/resource/doc/badges/badge_doc.svg
glabpkg/pkg_dev/resource/doc/badges/listing.rst
glabpkg/pkg_dev/resource/doc/biblio/biblio.rst
glabpkg/pkg_dev/resource/doc/user/index.rst
glabpkg/pkg_dev/resource/doc/user/overview.rst
glabpkg/pkg_dev/resource/example/readme.rst
glabpkg/pkg_dev/resource/test/test_packaging.py.tpl
glabpkg/report/__init__.py
glabpkg/report/option.py
glabpkg/report/resource/.gitlab-ci.yml
glabpkg/report/resource/README.rst
glabpkg/report/resource/report/authors.rst
glabpkg/report/resource/report/conf.py.tpl
glabpkg/report/resource/report/index.rst
glabpkg-4.2.0.dist-info/AUTHORS.rst
glabpkg-4.2.0.dist-info/LICENSE
glabpkg-4.2.0.dist-info/METADATA
glabpkg-4.2.0.dist-info/WHEEL
glabpkg-4.2.0.dist-info/entry_points.txt
glabpkg-4.2.0.dist-info/top_level.txt
glabpkg-4.2.0.dist-info/RECORD
